docs/conf.py
tests/__init__.py
tests/test_bcs.py
tests/test_load_planet.py
tests/test_metals.py
tests/test_misc.py
tests/test_physics.py
tests/test_polish_bcs.py
tests/test_ramp_to.py
tests/test_run_wind.py
tests/test_spectrum.py
tests/test_system.py
tests/test_windsoln.py
wind_ae/__init__.py
wind_ae/setup.py
wind_ae/McAstro/__init__.py
wind_ae/McAstro/atoms/Lodders.dat
wind_ae/McAstro/atoms/Verner.csv
wind_ae/McAstro/atoms/__init__.py
wind_ae/McAstro/atoms/atomic_masses.csv
wind_ae/McAstro/atoms/atomic_species.py
wind_ae/McAstro/atoms/atomic_table.txt
wind_ae/McAstro/atoms/solarZ_mass_fracs.csv
wind_ae/McAstro/planets/Ballistic.py
wind_ae/McAstro/planets/__init__.py
wind_ae/McAstro/planets/atmosphere.py
wind_ae/McAstro/planets/insolation/euv.py
wind_ae/McAstro/planets/insolation/glq_rates.py
wind_ae/McAstro/planets/insolation/glq_spectrum.py
wind_ae/McAstro/planets/insolation/stellar_euv.py
wind_ae/McAstro/radiation/__init__.py
wind_ae/McAstro/radiation/image_plane.py
wind_ae/McAstro/radiation/imaging.py
wind_ae/McAstro/radiation/radiative_transfer.py
wind_ae/McAstro/radiation/ray_trace.py
wind_ae/McAstro/radiation/rtw.py
wind_ae/McAstro/radiation/lines/CII_1.py
wind_ae/McAstro/radiation/lines/chiantiline.py
wind_ae/McAstro/radiation/lines/lyman_alpha.py
wind_ae/McAstro/radiation/ray_generators/relax_ray.py
wind_ae/McAstro/radiation/ray_generators/yt_ray.py
wind_ae/McAstro/stars/__init__.py
wind_ae/McAstro/stars/classification/mass_classification.py
wind_ae/McAstro/stars/relations/colour_relation.py
wind_ae/McAstro/stars/relations/mass_relation.py
wind_ae/McAstro/stars/relations/temperature_relation.py
wind_ae/McAstro/stars/relations/colour_relation_models/Mamajek2008.py
wind_ae/McAstro/stars/relations/mass_relation_models/Eker2018.py
wind_ae/McAstro/stars/relations/temperature_relation_models/Ballesteros2012.py
wind_ae/McAstro/stars/relations/temperature_relation_models/Sung2013.py
wind_ae/McAstro/stars/spectrum/black_body.py
wind_ae-0.5.10.dist-info/licenses/LICENSE
wind_ae-0.5.10.dist-info/METADATA
wind_ae-0.5.10.dist-info/WHEEL
wind_ae-0.5.10.dist-info/top_level.txt
wind_ae-0.5.10.dist-info/RECORD
