Metadata-Version: 2.4
Name: wind_ae
Version: 0.5.10
Summary: 1D relaxation Parker wind model with metal and X-ray physics based on Murray-Clay et al. (2009)
Author: Madelyn Broome, John McCann, Ruth Murray-Clay
License-Expression: BSD-3-Clause
Project-URL: Homepage, https://github.com/mibroome/wind_ae
Project-URL: Issues, https://github.com/mibroome/wind_ae/issues
Classifier: Programming Language :: Python :: 3
Classifier: Operating System :: OS Independent
Requires-Python: >=3.13
License-File: LICENSE
Requires-Dist: scipy>1.6
Requires-Dist: numpy
Requires-Dist: astropy
Requires-Dist: IPython
Requires-Dist: pandas>=2.2.3
Requires-Dist: matplotlib
Requires-Dist: datetime
Requires-Dist: pyarrow
Requires-Dist: fastparquet
Requires-Dist: requests
Requires-Dist: ChiantiPy
Requires-Dist: pytest
Dynamic: license-file
